<?xml version="1.0" encoding="UTF-8"?>
<record_update table="sp_instance">
    <sp_instance action="INSERT_OR_UPDATE">
        <active>true</active>
        <class_name/>
        <color>default</color>
        <css/>
        <glyph/>
        <id/>
        <order>1</order>
        <roles/>
        <short_description/>
        <size>md</size>
        <sp_column display_value="1">7d3c5420dbab9340d087d8965e96195d</sp_column>
        <sp_widget display_value="Add New Asset">ae4c1420dbab9340d087d8965e9619fa</sp_widget>
        <sys_class_name>sp_instance</sys_class_name>
        <sys_created_by>212606938</sys_created_by>
        <sys_created_on>2018-07-23 13:30:38</sys_created_on>
        <sys_customer_update>false</sys_customer_update>
        <sys_id>a08d90e0dbab9340d087d8965e9619dd</sys_id>
        <sys_mod_count>0</sys_mod_count>
        <sys_name/>
        <sys_package display_value="Asset Scanning" source="x_gege9_asset_scan">7be151dddbe55700d087d8965e9619c8</sys_package>
        <sys_policy/>
        <sys_replace_on_upgrade>false</sys_replace_on_upgrade>
        <sys_scope display_value="Asset Scanning">7be151dddbe55700d087d8965e9619c8</sys_scope>
        <sys_update_name>sp_instance_a08d90e0dbab9340d087d8965e9619dd</sys_update_name>
        <sys_updated_by>212606938</sys_updated_by>
        <sys_updated_on>2018-07-23 13:30:38</sys_updated_on>
        <title/>
        <url/>
        <widget_parameters/>
    </sp_instance>
    <sys_translated_text action="delete_multiple" query="documentkey=a08d90e0dbab9340d087d8965e9619dd"/>
</record_update>
